LICENSE
README.md
setup.py
src/RepeatRanger/__init__.py
src/RepeatRanger/prototype_assembly.py
src/RepeatRanger/prototype_raw.py
src/RepeatRanger.egg-info/PKG-INFO
src/RepeatRanger.egg-info/SOURCES.txt
src/RepeatRanger.egg-info/dependency_links.txt
src/RepeatRanger.egg-info/entry_points.txt
src/RepeatRanger.egg-info/requires.txt
src/RepeatRanger.egg-info/top_level.txt
src/RepeatRanger/tools/__init__.py
src/RepeatRanger/tools/graph.py
src/RepeatRanger/tools/helpers.py