Metadata-Version: 2.1
Name: RepeatRanger
Version: 0.1.1
Summary: De Novo Repeat Annotation Tool for Assembled Genomes.
Home-page: https://github.com/ad3002/RepeatRanger
Author: Aleksey Komissarov
Author-email: ad3002@gmail.com
License: BSD
Classifier: Development Status :: 4 - Beta
Classifier: Environment :: Console
Classifier: Intended Audience :: Science/Research
Classifier: License :: OSI Approved :: BSD License
Classifier: Operating System :: OS Independent
Classifier: Programming Language :: Python
Classifier: Topic :: Scientific/Engineering :: Bio-Informatics
Requires-Python: >=3.6
License-File: LICENSE
